imessagedb/__init__.py
imessagedb/__main__.py
imessagedb/attachment.py
imessagedb/attachments.py
imessagedb/chat.py
imessagedb/chats.py
imessagedb/db.py
imessagedb/default.ini
imessagedb/generate_html.py
imessagedb/generate_text.py
imessagedb/handle.py
imessagedb/handles.py
imessagedb/message.py
imessagedb/messages.py
imessagedb/utils.py
imessagedb-1.4.7.dist-info/LICENSE
imessagedb-1.4.7.dist-info/METADATA
imessagedb-1.4.7.dist-info/WHEEL
imessagedb-1.4.7.dist-info/entry_points.txt
imessagedb-1.4.7.dist-info/RECORD
