Metadata-Version: 2.1
Name: imessagedb
Version: 1.4.7
Summary: Reads and displays the Apple iMessage database
License: MIT
Author: xev
Author-email: git@schore.org
Requires-Python: >=3.9,<4.0
Classifier: License :: OSI Approved :: MIT License
Classifier: Programming Language :: Python :: 3
Classifier: Programming Language :: Python :: 3.9
Classifier: Programming Language :: Python :: 3.10
Classifier: Programming Language :: Python :: 3.11
Classifier: Programming Language :: Python :: 3.12
Requires-Dist: alive-progress (>=3.1.2,<4.0.0)
Requires-Dist: configparser (>=5.3.0,<6.0.0)
Requires-Dist: ffmpeg-python (>=0.2.0,<0.3.0)
Requires-Dist: heic2png (>=1.0.0,<2.0.0)
Requires-Dist: python-dateutil (>=2.8.2,<3.0.0)
Requires-Dist: termcolor (>=2.3.0,<3.0.0)
